universalinit_env/__init__.py
universalinit_env/angular/env.template
universalinit_env/astro/env.template
universalinit_env/envmapper.py
universalinit_env/lightningjs/env.template
universalinit_env/nextjs/env.template
universalinit_env/nuxt/env.template
universalinit_env/postgresql/env.template
universalinit_env/qwik/env.template
universalinit_env/react/env.template
universalinit_env/reactnative/env.template
universalinit_env/remix/env.template
universalinit_env/remotion/env.template
universalinit_env/slidev/env.template
universalinit_env/solananextjs/env.template
universalinit_env/svelte/env.template
universalinit_env/typescript/env.template
universalinit_env/vite/env.template
universalinit_env/vue/env.template
universalinit_env-0.1.10.dist-info/METADATA
universalinit_env-0.1.10.dist-info/WHEEL
universalinit_env-0.1.10.dist-info/RECORD
