Metadata-Version: 2.1
Name: universalinit-env
Version: 0.1.10
Summary: Environment variable mapping utilities for UniversalInit framework
Author: Zoltan Kuscsik
Author-email: zoltan@s57.io
Requires-Python: >=3.11,<4.0
Classifier: Programming Language :: Python :: 3
Classifier: Programming Language :: Python :: 3.11
Classifier: Programming Language :: Python :: 3.12
Requires-Dist: PyYAML (>=6.0,<7.0)
